solaxx3rs485.py
solax_x3_rs485-0.0.2.dist-info/LICENSE
solax_x3_rs485-0.0.2.dist-info/METADATA
solax_x3_rs485-0.0.2.dist-info/WHEEL
solax_x3_rs485-0.0.2.dist-info/top_level.txt
solax_x3_rs485-0.0.2.dist-info/RECORD
