Metadata-Version: 2.1
Name: solax-x3-rs485
Version: 0.0.2
Summary: A library to read information from your Solax X3 solar inverter through its RS485 port
Home-page: https://github.com/jvdslikke/py-solax-x3-rs485
Author: Johan van der Slikke
Author-email: johan@vdslikke.net
License: UNKNOWN
Project-URL: Bug Tracker, https://github.com/jvdslikke/py-solax-x3-rs485/issues
Platform: UNKNOWN
Classifier: Programming Language :: Python :: 3
Classifier: License :: OSI Approved :: MIT License
Classifier: Operating System :: OS Independent
Classifier: Development Status :: 4 - Beta
Classifier: Intended Audience :: Developers
Classifier: Topic :: Home Automation
Classifier: Topic :: Software Development :: Libraries :: Python Modules
Requires-Python: >=3.6
License-File: LICENSE
